zmapsdk/__init__.py
zmapsdk/__main__.py
zmapsdk/api.py
zmapsdk/cli.py
zmapsdk/config.py
zmapsdk/core.py
zmapsdk/exceptions.py
zmapsdk/input.py
zmapsdk/output.py
zmapsdk/parser.py
zmapsdk/runner.py
zmapsdk/schemas.py
zmapsdk-0.1.4.dist-info/LICENSE
zmapsdk-0.1.4.dist-info/METADATA
zmapsdk-0.1.4.dist-info/WHEEL
zmapsdk-0.1.4.dist-info/RECORD
