Metadata-Version: 2.3
Name: zmapsdk
Version: 0.1.4
Summary: Python SDK for the ZMap network scanner
License: MIT
Author: Happy Hacking Space
Author-email: team@happyhacking.space
Requires-Python: >=3.10
Classifier: Development Status :: 4 - Beta
Classifier: Intended Audience :: Developers
Classifier: Intended Audience :: Information Technology
Classifier: Intended Audience :: System Administrators
Classifier: License :: OSI Approved :: MIT License
Classifier: Operating System :: POSIX :: Linux
Classifier: Programming Language :: Python :: 3
Classifier: Programming Language :: Python :: 3.10
Classifier: Programming Language :: Python :: 3.11
Classifier: Programming Language :: Python :: 3.12
Classifier: Programming Language :: Python :: 3.13
Classifier: Topic :: Security
Classifier: Topic :: System :: Networking
Requires-Dist: click (>=8.1.8,<9.0.0)
Requires-Dist: fastapi (>=0.100.0)
Requires-Dist: httpx (>=0.28.1,<0.29.0)
Requires-Dist: psutil (>=7.0.0,<8.0.0)
Requires-Dist: tomli (>=2.0.1,<3.0.0)
Requires-Dist: tomlkit (>=0.13.2,<0.14.0)
Requires-Dist: uvicorn (>=0.22.0)
Project-URL: Repository, https://github.com/HappyHackingSpace/ZmapSDK
